applicationmapper.py
main.py
utils.py
applicationmapper-0.3.1.dist-info/METADATA
applicationmapper-0.3.1.dist-info/WHEEL
applicationmapper-0.3.1.dist-info/entry_points.txt
applicationmapper-0.3.1.dist-info/RECORD
