Metadata-Version: 2.4
Name: applicationmapper
Version: 0.3.1
Summary: Implements the `ApplicationMapper` CRD on top of Metacontroller.
Requires-Python: >=3.13
Requires-Dist: databind>=4.5.2
Requires-Dist: flask>=3.1.0
Requires-Dist: kubernetes>=31.0.0
Requires-Dist: loguru>=0.7.3
Requires-Dist: metacontroller-api>=0.2.0
Requires-Dist: python-jsonpath>=1.2.2
Requires-Dist: pyyaml>=6.0.2
Requires-Dist: requests>=2.32.3
Requires-Dist: typer>=0.15.1
